sqs_polling/__init__.py
sqs_polling/__main__.py
sqs_polling/__version__.py
sqs_polling/exceptions.py
sqs_polling/execute_result.py
sqs_polling/handler.py
sqs_polling/main.py
sqs_polling/polling.py
sqs_polling/signal.py
sqs_polling/types.py
sqs_polling/utils.py
sqs_apolling-0.0.5.dist-info/LICENSE
sqs_apolling-0.0.5.dist-info/METADATA
sqs_apolling-0.0.5.dist-info/WHEEL
sqs_apolling-0.0.5.dist-info/entry_points.txt
sqs_apolling-0.0.5.dist-info/top_level.txt
sqs_apolling-0.0.5.dist-info/RECORD
