Metadata-Version: 2.1
Name: sqs-apolling
Version: 0.0.5
Summary: Poll AWS SQS using asyncio and execute callback.
Home-page: https://github.com/nonchan7720/sqs-polling
Author: Nozomi nishinohara
Author-email: nozomi_nishinohara@n-creativesystem.com
License: MIT License
Project-URL: Code, https://github.com/nonchan7720/sqs-polling
Project-URL: Tracker, https://github.com/nonchan7720/sqs-polling/issues
Classifier: Development Status :: 1 - Planning
Classifier: Intended Audience :: Developers
Classifier: Topic :: System :: Distributed Computing
Classifier: Topic :: Software Development :: Libraries :: Python Modules
Classifier: License :: OSI Approved :: MIT License
Classifier: Operating System :: OS Independent
Classifier: Programming Language :: Python :: 3
Classifier: Programming Language :: Python :: 3.10
Requires-Python: >=3.10
License-File: LICENSE
Requires-Dist: boto3
Requires-Dist: asyncio
